tcmetatraderlinux/__init__.py
tcmetatraderlinux/__main__.py
tcmetatraderlinux-0.3.0.dist-info/LICENSE.txt
tcmetatraderlinux-0.3.0.dist-info/METADATA
tcmetatraderlinux-0.3.0.dist-info/WHEEL
tcmetatraderlinux-0.3.0.dist-info/top_level.txt
tcmetatraderlinux-0.3.0.dist-info/RECORD
