Metadata-Version: 2.1
Name: tcmetatraderlinux
Version: 0.3.0
Summary: MetaTrader5 for linux users
Home-page: https://github.com/Traders-Connect/mt5linux-tc
Author: Lucas Prett Campagna
License: MIT
License-File: LICENSE.txt
Requires-Dist: numpy
Requires-Dist: plumbum ==1.7.0
Requires-Dist: pyparsing ==2.4.7
Requires-Dist: rpyc ==5.2.3
